redis_command_generator/AllGen.py
redis_command_generator/BaseGen.py
redis_command_generator/BitmapGen.py
redis_command_generator/BloomGen.py
redis_command_generator/CmsGen.py
redis_command_generator/CuckooGen.py
redis_command_generator/GenRunner.py
redis_command_generator/GeoGen.py
redis_command_generator/HashGen.py
redis_command_generator/HyperLogLogGen.py
redis_command_generator/JsonGen.py
redis_command_generator/ListGen.py
redis_command_generator/SetGen.py
redis_command_generator/StreamGen.py
redis_command_generator/StringGen.py
redis_command_generator/TDigestGen.py
redis_command_generator/TimeSeriesGen.py
redis_command_generator/TopKGen.py
redis_command_generator/ZSetGen.py
redis_command_generator/__init__.py
redis_command_generator/distributions.json
redis_command_generator-0.7.8.post2.dist-info/licenses/LICENSE
redis_command_generator-0.7.8.post2.dist-info/METADATA
redis_command_generator-0.7.8.post2.dist-info/WHEEL
redis_command_generator-0.7.8.post2.dist-info/top_level.txt
redis_command_generator-0.7.8.post2.dist-info/RECORD
