Metadata-Version: 2.4
Name: redis_command_generator
Version: 0.7.8.post2
Summary: Commands generator for Redis
Author-email: Itay Tzivony <itay.tzivony@redis.com>
Project-URL: Homepage, https://github.com/redislabsdev/command-generator
Project-URL: Issues, https://github.com/redislabsdev/command-generator/issues
Classifier: Programming Language :: Python :: 3
Classifier: Operating System :: OS Independent
Classifier: License :: Other/Proprietary License
Requires-Python: >=3.11
License-File: LICENSE
Requires-Dist: redis==5.2.1
Requires-Dist: simple_parsing
Dynamic: license-file
